[{
        "link": "#",
        "imgurl": "./images/img_banner01.gif"
    },
    {
        "link": "#",
        "imgurl": "./images/img_banner02.gif"
    },
    {
        "link": "#",
        "imgurl": "./images/img_banner03.gif"
    },
    {
        "link": "#",
        "imgurl": "./images/img_banner04.gif"
    },
    {
        "link": "#",
        "imgurl": "./images/img_banner05.gif"
    },
    {
        "link": "#",
        "imgurl": "./images/img_banner06.gif"
    },
    {
        "link": "#",
        "imgurl": "./images/img_banner07.gif"
    },
    {
        "link": "#",
        "imgurl": "./images/img_banner08.gif"
    },
    {
        "link": "#",
        "imgurl": "./images/img_banner09.gif"
    }
]